rabbitholer/__init__.py
rabbitholer/logger.py
rabbitholer/main.py
rabbitholer/rabbit_dumper.py
rabbitholer/version.py
tests/__init__.py
tests/test_args.py
tests/test_main_functions.py
rabbitholer-0.0.2.dist-info/LICENSE
rabbitholer-0.0.2.dist-info/METADATA
rabbitholer-0.0.2.dist-info/WHEEL
rabbitholer-0.0.2.dist-info/entry_points.txt
rabbitholer-0.0.2.dist-info/top_level.txt
rabbitholer-0.0.2.dist-info/RECORD
