Metadata-Version: 2.1
Name: rabbitholer
Version: 0.0.2
Summary: A simple tool to send and receive messages to and from rabbitmqexchanges and queues
Home-page: https://github.com/palikar/rabbitholer
Author: Stanislav Arnaudov
Author-email: stanislv_ts@abv.bg
License: GNU General Public License v3.0
Keywords: rabbitmq sender receiver
Platform: UNKNOWN
Classifier: Development Status :: 4 - Beta
Classifier: Intended Audience :: Developers
Classifier: Natural Language :: English
Classifier: License :: OSI Approved :: GNU General Public License v3 (GPLv3)
Classifier: Operating System :: POSIX :: Linux
Classifier: Programming Language :: Python :: 3.3
Classifier: Programming Language :: Python :: 3.4
Classifier: Programming Language :: Python :: 3.5
Classifier: Programming Language :: Python :: 3.6
Classifier: Programming Language :: Python :: 3.7
Classifier: Topic :: Software Development :: Libraries :: Python Modules
Classifier: Environment :: Console
Classifier: Topic :: System :: Logging
Classifier: Topic :: System :: Monitoring
Classifier: Topic :: Utilities
